load_floz.py
load_floz-0.1.0.dist-info/METADATA
load_floz-0.1.0.dist-info/WHEEL
load_floz-0.1.0.dist-info/top_level.txt
load_floz-0.1.0.dist-info/RECORD
