Metadata-Version: 2.1
Name: load_floz
Version: 0.1.0
Summary: Load .floz files saved by Fast Lock On (FLO) tracking
Author-email: Andrew Straw <strawman@astraw.com>
Project-URL: Homepage, https://github.com/strawlab/flo-data-analysis
Classifier: Development Status :: 4 - Beta
Classifier: Intended Audience :: Developers
Classifier: License :: OSI Approved :: MIT License
Classifier: Programming Language :: Python
Requires-Python: >=3.8
Requires-Dist: pandas
Requires-Dist: PyYAML
Requires-Dist: pytz
